{
  "report_type": "libu_documentation_report",
  "version": "v2.77.0",
  "date": "2026-03-16",
  "department": "礼部",
  "department_role": "品牌营销、内容创作",
  "project": "nas-os",
  "project_path": "/home/mrafter/clawd/nas-os",
  "summary": {
    "tasks_total": 6,
    "tasks_completed": 6,
    "documents_updated": 13,
    "documents_created": 2
  },
  "tasks": [
    {
      "id": 1,
      "name": "检查 docs/ 目录下的文档完整性",
      "status": "completed",
      "details": "识别了所有需要更新的文档，检查了核心文档、API文档、用户指南等"
    },
    {
      "id": 2,
      "name": "更新 CHANGELOG.md",
      "status": "completed",
      "details": "添加了 v2.77.0 条目，包含文档体系完善和版本号统一更新"
    },
    {
      "id": 3,
      "name": "更新 README.md",
      "status": "completed",
      "details": "更新版本号至 v2.77.0，更新下载链接和 Docker 镜像版本"
    },
    {
      "id": 4,
      "name": "完善 API 文档 docs/api/",
      "status": "completed",
      "details": "更新了 docs/api/README.md 和 docs/api/examples.md 的版本号"
    },
    {
      "id": 5,
      "name": "创建或更新用户指南",
      "status": "completed",
      "details": "更新了 docs/user-guide/README.md 的版本号（从 v2.72.0 到 v2.77.0）"
    },
    {
      "id": 6,
      "name": "生成工作报告",
      "status": "completed",
      "details": "创建了 libu_report.json 和 STATUS-v2.77.0.md"
    }
  ],
  "documents_updated": [
    {
      "file": "CHANGELOG.md",
      "change": "添加 v2.77.0 条目"
    },
    {
      "file": "README.md",
      "change": "版本号更新至 v2.77.0，下载链接更新"
    },
    {
      "file": "docs/README.md",
      "change": "文档中心索引版本更新"
    },
    {
      "file": "docs/README_EN.md",
      "change": "英文文档版本更新"
    },
    {
      "file": "docs/USER_GUIDE.md",
      "change": "用户指南版本更新"
    },
    {
      "file": "docs/QUICKSTART.md",
      "change": "快速开始指南版本更新"
    },
    {
      "file": "docs/FAQ.md",
      "change": "常见问题版本更新"
    },
    {
      "file": "docs/API_GUIDE.md",
      "change": "API 使用指南版本更新"
    },
    {
      "file": "docs/TROUBLESHOOTING.md",
      "change": "故障排查指南版本更新"
    },
    {
      "file": "docs/api/README.md",
      "change": "API 文档索引版本更新"
    },
    {
      "file": "docs/api/examples.md",
      "change": "API 示例代码版本更新"
    },
    {
      "file": "docs/user-guide/README.md",
      "change": "用户指南索引版本更新（从 v2.72.0）"
    },
    {
      "file": "docs/swagger/swagger.yaml",
      "change": "OpenAPI 规范版本更新"
    }
  ],
  "documents_created": [
    {
      "file": "docs/RELEASE-v2.77.0.md",
      "purpose": "v2.77.0 发布说明"
    },
    {
      "file": "docs/STATUS-v2.77.0.md",
      "purpose": "项目状态报告"
    }
  ],
  "documentation_structure": {
    "core_docs": [
      "README.md",
      "docs/README.md",
      "docs/QUICKSTART.md",
      "docs/USER_GUIDE.md",
      "docs/FAQ.md",
      "docs/API_GUIDE.md",
      "docs/TROUBLESHOOTING.md"
    ],
    "api_docs": [
      "docs/api/README.md",
      "docs/api/audit-api.md",
      "docs/api/billing-api.md",
      "docs/api/dashboard-api.md",
      "docs/api/health-api.md",
      "docs/api/invoice-api.md",
      "docs/api/monitor-api.md",
      "docs/api/permission-api.md",
      "docs/api/storage-api.md",
      "docs/api/user-api.md",
      "docs/api/examples.md"
    ],
    "user_guide_docs": [
      "docs/user-guide/README.md",
      "docs/user-guide/permission-guide.md",
      "docs/user-guide/backup-guide.md",
      "docs/user-guide/audit-guide.md",
      "docs/user-guide/billing-guide.md",
      "docs/user-guide/distributed-monitoring-guide.md",
      "docs/user-guide/dashboard-guide.md"
    ],
    "swagger_docs": [
      "docs/swagger/swagger.yaml",
      "docs/swagger/swagger.json",
      "docs/swagger/docs.go"
    ]
  },
  "notes": [
    "未修改版本号，只做文档更新",
    "未提交代码，只做文档更新和报告",
    "docs/user-guide/README.md 原版本为 v2.72.0，已更新至 v2.77.0"
  ],
  "generated_at": "2026-03-16T00:10:00+08:00"
}